cerial/__init__.py
cerial/cerial.py
pycerial-0.1.4.dist-info/LICENSE
pycerial-0.1.4.dist-info/METADATA
pycerial-0.1.4.dist-info/WHEEL
pycerial-0.1.4.dist-info/top_level.txt
pycerial-0.1.4.dist-info/RECORD
